mr_z3r0_calculator/__init__.py
mr_z3r0_calculator/basic.py
mr_z3r0_calculator-0.2.0.dist-info/licenses/LICENSE.txt
test/__init__.py
test/test_001_basic.py
mr_z3r0_calculator-0.2.0.dist-info/METADATA
mr_z3r0_calculator-0.2.0.dist-info/WHEEL
mr_z3r0_calculator-0.2.0.dist-info/top_level.txt
mr_z3r0_calculator-0.2.0.dist-info/RECORD
